[
  {
    "id": 0,
    "en1": "",
    "en2": "",
    "en3": "",
    "en4": "",
    "vn1": ""
  },
  {
    "id": 273,
    "en1": "Wise",
    "en2": "Wisdom",
    "en3": "Wisely",
    "en4": "",
    "vn1": "Từng trải,hiểu biết nhiều"
  },
  {
    "id": 272,
    "en1": "Return",
    "en2": "Returns",
    "en3": "Returnable",
    "en4": "",
    "vn1": "Tiền thu về, lợi nhuận"
  },
  {
    "id": 271,
    "en1": "Resource",
    "en2": "",
    "en3": "",
    "en4": "",
    "vn1": "Tài sản"
  },
  {
    "id": 270,
    "en1": "Pull out",
    "en2": "",
    "en3": "",
    "en4": "",
    "vn1": "Sự rút lui"
  },
  {
    "id": 269,
    "en1": "Portfolio",
    "en2": "",
    "en3": "",
    "en4": "",
    "vn1": "Danh mục vốn đầu tư"
  },
  {
    "id": 268,
    "en1": "Long-term",
    "en2": "",
    "en3": "",
    "en4": "",
    "vn1": "Dài hạn"
  },
  {
    "id": 267,
    "en1": "Invest",
    "en2": "Investment",
    "en3": "Investor",
    "en4": "",
    "vn1": "Đầu tư,Sự đầu tư, người đầu tư"
  },
  {
    "id": 266,
    "en1": "Fund",
    "en2": "",
    "en3": "",
    "en4": "",
    "vn1": "Quỹ"
  },
  {
    "id": 265,
    "en1": "Conservative",
    "en2": "",
    "en3": "",
    "en4": "",
    "vn1": "Bảo thủ"
  },
  {
    "id": 264,
    "en1": "Commitment",
    "en2": "Commit",
    "en3": "Noncommittal",
    "en4": "",
    "vn1": "Lời cam kết, Cam kết"
  },
  {
    "id": 263,
    "en1": "Attitude",
    "en2": "",
    "en3": "",
    "en4": "",
    "vn1": "Thái độ"
  },
  {
    "id": 262,
    "en1": "Aggressive",
    "en2": "",
    "en3": "",
    "en4": "",
    "vn1": "Có sức cạnh tranh"
  }
]
