[
  {
    "id": 0,
    "en1": "",
    "en2": "",
    "en3": "",
    "en4": "",
    "vn1": ""
  },
  {
    "id": 396,
    "en1": "settle",
    "en2": "",
    "en3": "",
    "en4": "",
    "vn1": "bố trí, dàn xếp"
  },
  {
    "id": 395,
    "en1": "pick up",
    "en2": "",
    "en3": "",
    "en4": "",
    "vn1": "đón"
  },
  {
    "id": 394,
    "en1": "narrow",
    "en2": "",
    "en3": "",
    "en4": "",
    "vn1": "chật, hẹp"
  },
  {
    "id": 393,
    "en1": "multiple",
    "en2": "",
    "en3": "",
    "en4": "",
    "vn1": "nhiều, nhiều phần"
  },
  {
    "id": 392,
    "en1": "list",
    "en2": "",
    "en3": "",
    "en4": "",
    "vn1": "danh sách, bản kê khai"
  },
  {
    "id": 391,
    "en1": "individual",
    "en2": "",
    "en3": "",
    "en4": "",
    "vn1": "cá nhân, riêng biệt"
  },
  {
    "id": 390,
    "en1": "impress",
    "en2": "",
    "en3": "",
    "en4": "",
    "vn1": "gây ấn tượng"
  },
  {
    "id": 389,
    "en1": "fall to",
    "en2": "",
    "en3": "",
    "en4": "",
    "vn1": "bắt tay vào việc"
  },
  {
    "id": 388,
    "en1": "elegance",
    "en2": "",
    "en3": "",
    "en4": "",
    "vn1": "thanh lịch, tao nhã"
  },
  {
    "id": 387,
    "en1": "delivery",
    "en2": "",
    "en3": "",
    "en4": "",
    "vn1": "giao hàng, phân phát"
  },
  {
    "id": 386,
    "en1": "commonly",
    "en2": "",
    "en3": "",
    "en4": "",
    "vn1": "thường thường, thông thường"
  },
  {
    "id": 385,
    "en1": "burden",
    "en2": "",
    "en3": "",
    "en4": "",
    "vn1": "gánh nặng"
  }
]
