[
  {
    "id": 0,
    "en1": "",
    "en2": "",
    "en3": "",
    "en4": "",
    "vn1": ""
  },
  {
    "id": 264,
    "en1": "turnover",
    "en2": "",
    "en3": "",
    "en4": "",
    "vn1": "doanh số, doanh thu"
  },
  {
    "id": 263,
    "en1": "reconcile",
    "en2": "",
    "en3": "",
    "en4": "",
    "vn1": "hòa giải, giảng hòa"
  },
  {
    "id": 262,
    "en1": "profitably",
    "en2": "",
    "en3": "",
    "en4": "",
    "vn1": "có lợi, có ích"
  },
  {
    "id": 261,
    "en1": "outstanding",
    "en2": "",
    "en3": "",
    "en4": "",
    "vn1": "còn tồn tại, chưa trả nợ"
  },
  {
    "id": 260,
    "en1": "debt",
    "en2": "",
    "en3": "",
    "en4": "",
    "vn1": "món nợ"
  },
  {
    "id": 259,
    "en1": "client",
    "en2": "",
    "en3": "",
    "en4": "",
    "vn1": "khách hàng"
  },
  {
    "id": 258,
    "en1": "build up",
    "en2": "",
    "en3": "",
    "en4": "",
    "vn1": "tăng cường"
  },
  {
    "id": 257,
    "en1": "budget",
    "en2": "",
    "en3": "",
    "en4": "",
    "vn1": "ngân sách, ngân quỹ"
  },
  {
    "id": 256,
    "en1": "audit",
    "en2": "",
    "en3": "",
    "en4": "",
    "vn1": "kiểm toán"
  },
  {
    "id": 255,
    "en1": "asset",
    "en2": "",
    "en3": "",
    "en4": "",
    "vn1": "tài sản"
  },
  {
    "id": 254,
    "en1": "accumulate",
    "en2": "",
    "en3": "",
    "en4": "",
    "vn1": "tích lũy, tích góp"
  },
  {
    "id": 253,
    "en1": "accounting",
    "en2": "",
    "en3": "",
    "en4": "",
    "vn1": "công việc kế toán"
  }
]
